<?xml version="1.0" encoding="UTF-8"?>
<!--Sample XML file generated by XMLSpy v2011 sp1 (http://www.altova.com)-->
<MRNAllocated xsi:noNamespaceSchemaLocation="MRNAllocated.xsd" xmlns:xsi="http://www.w3.org/2001/XMLSchema-instance">
	<GoodsDeclaration>
		<ReferenceNumber>text</ReferenceNumber>
		<UCRNumber>text</UCRNumber>
		<AcceptanceDate>00000000</AcceptanceDate>
		<PrincipalTIN>
			<TIN>String</TIN>
			<IsTINGermanApprovalNumber>true</IsTINGermanApprovalNumber>
			<CustomerIdentifier>String</CustomerIdentifier>
			<BO>aaaa</BO>
			<IdentificationType>String</IdentificationType>
		</PrincipalTIN>
		<Principal>
			<VATNumber>String</VATNumber>
			<ETNAddress>String</ETNAddress>
			<Address>
				<Name>String</Name>
				<Street>String</Street>
				<HouseNumber>String</HouseNumber>
				<City>String</City>
				<PostalCode>String</PostalCode>
				<Country>aa</Country>
				<CountrySubEntity>String</CountrySubEntity>
			</Address>
		</Principal>
		<OfficeOfDeparture>aaaaaaaa</OfficeOfDeparture>
		<PDFInformation>
			<Name>String</Name>
			<Directory>String</Directory>
			<NewDirectory>String</NewDirectory>
			<base64>UjBsR09EbGhjZ0dTQUxNQUFBUUNBRU1tQ1p0dU1GUXhEUzhi</base64>
		</PDFInformation>
		<TydenSealNumber>text</TydenSealNumber>
	</GoodsDeclaration>
</MRNAllocated>
